docs/Makefile
docs/make.bat
docs/source/conf.py
docs/source/index.rst
pyease/__init__.py
pyease/ease.py
pyease/easeexceptions.py
tests/test_pyease.py
pyease-0.2.0.dist-info/METADATA
pyease-0.2.0.dist-info/WHEEL
pyease-0.2.0.dist-info/top_level.txt
pyease-0.2.0.dist-info/RECORD
