Metadata-Version: 2.1
Name: pyease
Version: 0.2.0
Summary: Python Library with helpful functions for the Eclipse Advanced Scripting Environment (EASE). See https://www.eclipse.org/ease
Author: DB Netz AG
License: Apache-2.0
Project-URL: Homepage, https://github.com/DSD-DBS/pyease
Project-URL: Documentation, https://dsd-dbs.github.io/pyease
Platform: any
Classifier: Development Status :: 1 - Planning
Classifier: License :: OSI Approved :: Apache Software License
Classifier: Natural Language :: English
Classifier: Operating System :: OS Independent
Classifier: Programming Language :: Python :: 3 :: Only
Classifier: Programming Language :: Python :: 3.9
Classifier: Programming Language :: Python :: 3.10
Requires-Python: <3.12,>=3.10
Provides-Extra: dev
Requires-Dist: black ; extra == 'dev'
Requires-Dist: ipython ; extra == 'dev'
Requires-Dist: mccabe ; extra == 'dev'
Requires-Dist: pdbpp ; extra == 'dev'
Requires-Dist: pylint ; extra == 'dev'
Requires-Dist: pyls-isort ; extra == 'dev'
Requires-Dist: pylsp-mypy ; extra == 'dev'
Requires-Dist: python-lsp-black ; extra == 'dev'
Requires-Dist: python-lsp-server ; extra == 'dev'
Provides-Extra: docs
Requires-Dist: sphinx ; extra == 'docs'
Requires-Dist: sphinx-rtd-theme ; extra == 'docs'
Requires-Dist: tomli ; (python_version < "3.12") and extra == 'docs'
Provides-Extra: test
Requires-Dist: pytest ; extra == 'test'
Requires-Dist: pytest-cov ; extra == 'test'
